setup.cfg
setup.py
teradata/__init__.py
teradata/api.py
teradata/datatypes.py
teradata/pulljson.py
teradata/tdodbc.py
teradata/tdrest.py
teradata/udaexec.py
teradata/util.py
teradata/version.py
teradata.egg-info/PKG-INFO
teradata.egg-info/SOURCES.txt
teradata.egg-info/dependency_links.txt
teradata.egg-info/top_level.txt
teradata.egg-info/zip-safe
test/test_gc.py
test/test_pulljson.py
test/test_tdodbc.py
test/test_tdrest.py
test/test_udaexec_config.py
test/test_udaexec_datatypes.py
test/test_udaexec_execute.py